[
    {
        "key": "group_pf_global_context",
        "title": "Global Context (Profile)",
        "fields": [
            {
                "key": "field_pf_company_name",
                "label": "Company Name",
                "name": "company_name",
                "aria-label": "",
                "type": "text",
                "instructions": "",
                "required": 0,
                "conditional_logic": 0,
                "wrapper": {
                    "width": "",
                    "class": "",
                    "id": ""
                },
                "default_value": "",
                "maxlength": "",
                "allow_in_bindings": 0,
                "placeholder": "",
                "prepend": "",
                "append": ""
            },
            {
                "key": "field_pf_industry",
                "label": "Industry",
                "name": "industry",
                "aria-label": "",
                "type": "text",
                "instructions": "",
                "required": 0,
                "conditional_logic": 0,
                "wrapper": {
                    "width": "",
                    "class": "",
                    "id": ""
                },
                "default_value": "",
                "maxlength": "",
                "allow_in_bindings": 0,
                "placeholder": "",
                "prepend": "",
                "append": ""
            },
            {
                "key": "field_pf_tone",
                "label": "Tone of Voice",
                "name": "tone_of_voice",
                "aria-label": "",
                "type": "text",
                "instructions": "",
                "required": 0,
                "conditional_logic": 0,
                "wrapper": {
                    "width": "",
                    "class": "",
                    "id": ""
                },
                "default_value": "",
                "maxlength": "",
                "allow_in_bindings": 0,
                "placeholder": "",
                "prepend": "",
                "append": ""
            },
            {
                "key": "field_pf_audience",
                "label": "Target Audience",
                "name": "target_audience",
                "aria-label": "",
                "type": "textarea",
                "instructions": "",
                "required": 0,
                "conditional_logic": 0,
                "wrapper": {
                    "width": "",
                    "class": "",
                    "id": ""
                },
                "default_value": "",
                "maxlength": "",
                "allow_in_bindings": 0,
                "rows": "",
                "placeholder": "",
                "new_lines": ""
            },
            {
                "key": "field_pf_mission",
                "label": "Mission & Values",
                "name": "mission_values",
                "aria-label": "",
                "type": "textarea",
                "instructions": "",
                "required": 0,
                "conditional_logic": 0,
                "wrapper": {
                    "width": "",
                    "class": "",
                    "id": ""
                },
                "default_value": "",
                "maxlength": "",
                "allow_in_bindings": 0,
                "rows": "",
                "placeholder": "",
                "new_lines": ""
            },
            {
                "key": "field_pf_refs",
                "label": "Reference Examples",
                "name": "reference_examples",
                "aria-label": "",
                "type": "repeater",
                "instructions": "Examples or links that represent 'good output' for your brand.",
                "required": 0,
                "conditional_logic": 0,
                "wrapper": {
                    "width": "",
                    "class": "",
                    "id": ""
                },
                "layout": "table",
                "pagination": 0,
                "min": 0,
                "max": 0,
                "collapsed": "",
                "button_label": "Add Reference",
                "rows_per_page": 20,
                "sub_fields": [
                    {
                        "key": "field_pf_ref_title",
                        "label": "Title",
                        "name": "title",
                        "aria-label": "",
                        "type": "text",
                        "instructions": "",
                        "required": 0,
                        "conditional_logic": 0,
                        "wrapper": {
                            "width": "",
                            "class": "",
                            "id": ""
                        },
                        "default_value": "",
                        "maxlength": "",
                        "allow_in_bindings": 0,
                        "placeholder": "",
                        "prepend": "",
                        "append": ""
                    },
                    {
                        "key": "field_pf_ref_link",
                        "label": "Link or Text",
                        "name": "ref_text_or_link",
                        "aria-label": "",
                        "type": "textarea",
                        "instructions": "",
                        "required": 0,
                        "conditional_logic": 0,
                        "wrapper": {
                            "width": "",
                            "class": "",
                            "id": ""
                        },
                        "default_value": "",
                        "maxlength": "",
                        "allow_in_bindings": 0,
                        "rows": "",
                        "placeholder": "",
                        "new_lines": ""
                    }
                ]
            }
        ],
        "location": [
            [
                {
                    "param": "options_page",
                    "operator": "==",
                    "value": "acf-options-global-context"
                }
            ]
        ],
        "menu_order": 0,
        "position": "normal",
        "style": "default",
        "label_placement": "top",
        "instruction_placement": "label",
        "hide_on_screen": "",
        "active": true,
        "description": "",
        "show_in_rest": 0
    }
]
